<pragmas>
<pragma file="./src/matrix_mul.cpp" line="76" pragmaType="pipeline" parentfunction="matrix_mul" off="0" ii="1" rewind="0" style=""/>
<pragma file="./src/matrix_mul.cpp" line="63" pragmaType="pipeline" parentfunction="matrix_mul" off="0" ii="1" rewind="0" style=""/>
<pragma file="./src/matrix_mul.cpp" line="66" pragmaType="unroll" parentfunction="matrix_mul" factor="-1" skip_exit_check="0"/>
<pragma file="./src/matrix_mul.cpp" line="55" pragmaType="pipeline" parentfunction="matrix_mul" off="0" ii="1" rewind="0" style=""/>
<pragma file="./src/matrix_mul.cpp" line="47" pragmaType="pipeline" parentfunction="matrix_mul" off="0" ii="1" rewind="0" style=""/>
<pragma file="./src/matrix_mul.cpp" line="40" pragmaType="pipeline" parentfunction="matrix_mul" off="0" ii="1" rewind="0" style=""/>
<pragma file="./src/matrix_mul.cpp" line="18" pragmaType="interface" parentfunction="matrix_mul" mode="m_axi" port="A" bundle="gmem0" offset="slave" name="" depth="4096" num_read_outstanding="-1" num_write_outstanding="-1" max_burst_read_length="-1" max_burst_write_length="-1" latency="-1" max_widen_bitwidth="-1"/>
<pragma file="./src/matrix_mul.cpp" line="19" pragmaType="interface" parentfunction="matrix_mul" mode="m_axi" port="B" bundle="gmem1" offset="slave" name="" depth="4096" num_read_outstanding="-1" num_write_outstanding="-1" max_burst_read_length="-1" max_burst_write_length="-1" latency="-1" max_widen_bitwidth="-1"/>
<pragma file="./src/matrix_mul.cpp" line="20" pragmaType="interface" parentfunction="matrix_mul" mode="m_axi" port="C" bundle="gmem2" offset="slave" name="" depth="4096" num_read_outstanding="-1" num_write_outstanding="-1" max_burst_read_length="-1" max_burst_write_length="-1" latency="-1" max_widen_bitwidth="-1"/>
<pragma file="./src/matrix_mul.cpp" line="22" pragmaType="interface" parentfunction="matrix_mul" mode="s_axilite" port="A" bundle="control" offset="-1" name="" clock="" impl="" register="0"/>
<pragma file="./src/matrix_mul.cpp" line="23" pragmaType="interface" parentfunction="matrix_mul" mode="s_axilite" port="B" bundle="control" offset="-1" name="" clock="" impl="" register="0"/>
<pragma file="./src/matrix_mul.cpp" line="24" pragmaType="interface" parentfunction="matrix_mul" mode="s_axilite" port="C" bundle="control" offset="-1" name="" clock="" impl="" register="0"/>
<pragma file="./src/matrix_mul.cpp" line="25" pragmaType="interface" parentfunction="matrix_mul" mode="s_axilite" port="M" bundle="control" offset="-1" name="" clock="" impl="" register="0"/>
<pragma file="./src/matrix_mul.cpp" line="26" pragmaType="interface" parentfunction="matrix_mul" mode="s_axilite" port="N" bundle="control" offset="-1" name="" clock="" impl="" register="0"/>
<pragma file="./src/matrix_mul.cpp" line="27" pragmaType="interface" parentfunction="matrix_mul" mode="s_axilite" port="K" bundle="control" offset="-1" name="" clock="" impl="" register="0"/>
<pragma file="./src/matrix_mul.cpp" line="28" pragmaType="interface" parentfunction="matrix_mul" mode="s_axilite" port="" bundle="control" offset="-1" name="" clock="" impl="" register="0"/>
<pragma file="./src/matrix_mul.cpp" line="34" pragmaType="array_partition" parentfunction="matrix_mul" dim="2" factor="0" mode="complete" dynamic="0" variable=""/>
<pragma file="./src/matrix_mul.cpp" line="35" pragmaType="array_partition" parentfunction="matrix_mul" dim="1" factor="0" mode="complete" dynamic="0" variable=""/>
</pragmas>
